MANIFEST.in
README.rst
setup.py
version.py
.heroku/python/lib/python3.8/LICENSE.txt
.heroku/python/lib/python3.8/distutils/version.py
.heroku/python/lib/python3.8/site-packages/bleach/_vendor/README.rst
.heroku/python/lib/python3.8/site-packages/bleach/_vendor/html5lib-1.0.1.dist-info/LICENSE.txt
.heroku/python/lib/python3.8/site-packages/chardet/version.py
.heroku/python/lib/python3.8/site-packages/colorama-0.4.3.dist-info/LICENSE.txt
.heroku/python/lib/python3.8/site-packages/packaging/version.py
.heroku/python/lib/python3.8/site-packages/pip-20.1.1.dist-info/LICENSE.txt
.heroku/python/lib/python3.8/site-packages/pip/_vendor/chardet/version.py
.heroku/python/lib/python3.8/site-packages/pip/_vendor/distlib/version.py
.heroku/python/lib/python3.8/site-packages/pip/_vendor/packaging/version.py
.heroku/python/lib/python3.8/site-packages/pkg_resources/_vendor/packaging/version.py
.heroku/python/lib/python3.8/site-packages/pkginfo-1.5.0.1.dist-info/LICENSE.txt
.heroku/python/lib/python3.8/site-packages/requests-2.24.0.dist-info/LICENSE.txt
.heroku/python/lib/python3.8/site-packages/setuptools/version.py
.heroku/python/lib/python3.8/site-packages/setuptools/_vendor/packaging/version.py
.heroku/python/lib/python3.8/site-packages/urllib3-1.25.10.dist-info/LICENSE.txt
.heroku/python/lib/python3.8/site-packages/wheel-0.34.2.dist-info/LICENSE.txt
e_objects.egg-info/PKG-INFO
e_objects.egg-info/SOURCES.txt
e_objects.egg-info/dependency_links.txt
e_objects.egg-info/requires.txt
e_objects.egg-info/top_level.txt
objects/__init__.py