Metadata-Version: 1.1
Name: e-objects
Version: 1.0.4
Summary: Some useful objects for telegram bots.
Home-page: https://github.com/steve10live/e-objects/
Author: evolvestin
Author-email: evolvestin@gmail.com
License: MIT
Keywords: objects
Platform: UNKNOWN
Classifier: Development Status :: 5 - Production/Stable
Classifier: Intended Audience :: Developers
Classifier: Natural Language :: English
Classifier: License :: OSI Approved :: MIT License
Classifier: Programming Language :: Python
Classifier: Programming Language :: Python :: 3
Classifier: Programming Language :: Python :: 3.7
Classifier: Programming Language :: Python :: 3.8
